[
  {
    "title": "峰岡ハイツ",
    "address": "神奈川県横浜市保土ヶ谷区峰岡町２",
    "access": "相鉄本線/星川駅 歩141分 / 相鉄本線/和田町駅 歩14分 / ＪＲ東海道本線/横浜駅 バス15分 (バス停)峰岡上 歩1分",
    "age": 38,
    "rent": 45000,
    "management_fee": null,
    "deposit": 45000,
    "key_money": null,
    "layout": "1K",
    "area": 23.1
  },
  {
    "title": "里アパート",
    "address": "神奈川県横須賀市武１",
    "access": "ＪＲ横須賀線/衣笠駅 バス121分 (バス停)通信研究所入口 歩3分",
    "age": 51,
    "rent": 36000,
    "management_fee": null,
    "deposit": null,
    "key_money": null,
    "layout": "2DK",
    "area": 34.71
  },
  {
    "title": "リバーサイドグリーン",
    "address": "神奈川県横須賀市荻野",
    "access": "ＪＲ横須賀線/逗子駅 歩150分 / 京急本線/横須賀中央駅 歩112分 / ＪＲ横須賀線/横須賀駅 歩129分",
    "age": 18,
    "rent": 63000,
    "management_fee": 3500,
    "deposit": null,
    "key_money": 63000,
    "layout": "1LDK",
    "area": 42.98
  },
  {
    "title": "リバーサイドグリーン",
    "address": "神奈川県横須賀市荻野",
    "access": "ＪＲ横須賀線/逗子駅 歩150分 / 京急本線/横須賀中央駅 歩112分 / ＪＲ横須賀線/横須賀駅 歩129分",
    "age": 18,
    "rent": 72000,
    "management_fee": 3500,
    "deposit": null,
    "key_money": 82000,
    "layout": "1LDK",
    "area": 54.85
  },
  {
    "title": "東急東横線 綱島駅 4階建 築38年",
    "address": "神奈川県横浜市鶴見区駒岡４",
    "access": "東急東横線/綱島駅 バス121分 (バス停)八千代田 歩2分 / ＪＲ京浜東北線/鶴見駅 バス18分 (バス停)駒岡八幡神社 歩2分 / 東急新横浜線/新綱島駅 バス12分 (バス停)八千代田 歩2分",
    "age": 38,
    "rent": 98000,
    "management_fee": null,
    "deposit": null,
    "key_money": 98000,
    "layout": "3DK",
    "area": 49.5
  },
  {
    "title": "ミラソル佐島",
    "address": "神奈川県横須賀市佐島１",
    "access": "ＪＲ横須賀線/逗子駅 バス38分 (バス停)佐島１丁目 歩5分 / 京急逗子線/逗子・葉山駅 バス26分 (バス停)佐島一丁目 歩5分 / 京急本線/横須賀中央駅 バス39分 (バス停)佐島一丁目 歩5分",
    "age": 17,
    "rent": 61000,
    "management_fee": 4100,
    "deposit": null,
    "key_money": 61000,
    "layout": "1LDK",
    "area": 51.47
  },
  {
    "title": "ココペリ北里",
    "address": "神奈川県相模原市南区北里１",
    "access": "小田急線/相模大野駅 バス25分 (バス停)友愛病院前 歩9分 / 小田急小田原線/相武台前駅 バス16分 (バス停)友愛病院前 歩9分 / ＪＲ横浜線/相模原駅 バス18分 (バス停)友愛病院前 歩9分",
    "age": 2,
    "rent": 56000,
    "management_fee": 4000,
    "deposit": null,
    "key_money": null,
    "layout": "1K",
    "area": 19.44
  },
  {
    "title": "ココペリ北里",
    "address": "神奈川県相模原市南区北里１",
    "access": "小田急線/相模大野駅 バス25分 (バス停)友愛病院前 歩9分 / 小田急小田原線/相武台前駅 バス16分 (バス停)友愛病院前 歩9分 / ＪＲ横浜線/相模原駅 バス18分 (バス停)友愛病院前 歩9分",
    "age": 2,
    "rent": 57000,
    "management_fee": 4000,
    "deposit": null,
    "key_money": null,
    "layout": "1K",
    "area": 19.44
  },
  {
    "title": "小田急線 相模大野駅 2階建 新築",
    "address": "神奈川県相模原市南区北里１",
    "access": "小田急線/相模大野駅 バス37分 (バス停)北里大学病院・北里大学 歩121分 / / ＪＲ横浜線/古淵駅 バス36分 (バス停)北里大学病院・北里大学 歩12分",
    "age": 2,
    "rent": 56000,
    "management_fee": 4000,
    "deposit": null,
    "key_money": null,
    "layout": "ワンルーム",
    "area": 19.44
  },
  {
    "title": "小田急線 相模大野駅 2階建 新築",
    "address": "神奈川県相模原市南区北里１",
    "access": "小田急線/相模大野駅 バス37分 (バス停)北里大学病院・北里大学 歩121分 / / ＪＲ横浜線/古淵駅 バス36分 (バス停)北里大学病院・北里大学 歩12分",
    "age": 2,
    "rent": 57000,
    "management_fee": 4000,
    "deposit": null,
    "key_money": null,
    "layout": "1K",
    "area": 19.44
  },
  {
    "title": "レイクサイド三井",
    "address": "神奈川県相模原市緑区三井",
    "access": "ＪＲ横浜線/橋本駅 バス30分 (バス停)三井南 歩2分 / ＪＲ横浜線/相原駅 バス38分 (バス停)三井南 歩2分 / 京王相模原線/橋本駅 バス49分 (バス停)三井南 歩2分",
    "age": 35,
    "rent": 60000,
    "management_fee": 1000,
    "deposit": 60000,
    "key_money": 60000,
    "layout": "3DK",
    "area": 56.0
  },
  {
    "title": "ＫＳＧマリーンオークラNo.１５",
    "address": "神奈川県横浜市港北区樽町４",
    "access": "東急新横浜線/新綱島駅 歩15分 / 東急東横線/綱島駅 歩16分 / 東急東横線/大倉山駅 歩20分",
    "age": 29,
    "rent": 58000,
    "management_fee": 3500,
    "deposit": null,
    "key_money": null,
    "layout": "1K",
    "area": 19.84
  },
  {
    "title": "東急東横線 綱島駅 4階建 築29年",
    "address": "神奈川県横浜市港北区樽町４",
    "access": "東急東横線/綱島駅 歩16分 / 東急東横線/大倉山駅 歩20分 / グリーンライン/日吉本町駅 歩41分",
    "age": 29,
    "rent": 58000,
    "management_fee": 3500,
    "deposit": null,
    "key_money": null,
    "layout": "1K",
    "area": 19.84
  }
]